README.md
setup.py
analyseGoogleMyActivity/__init__.py
analyseGoogleMyActivity/androidReport.py
analyseGoogleMyActivity.egg-info/PKG-INFO
analyseGoogleMyActivity.egg-info/SOURCES.txt
analyseGoogleMyActivity.egg-info/dependency_links.txt
analyseGoogleMyActivity.egg-info/entry_points.txt
analyseGoogleMyActivity.egg-info/requires.txt
analyseGoogleMyActivity.egg-info/top_level.txt