Metadata-Version: 2.1
Name: analyseGoogleMyActivity
Version: 0.6
Summary: Generates Report of Sleep Time, Sleep Routine and App Usage using Data from Google MyActivity : myactivity.google.com
Home-page: https://github.com/superuser789/analyseGoogleMyActivity/
Author: Nitin Singh
Author-email: acc4nitin@gmail.com
License: MIT
Platform: UNKNOWN
Classifier: License :: OSI Approved :: MIT License
Classifier: Programming Language :: Python :: 3
Classifier: Programming Language :: Python :: 3.7
